MANIFEST.in
README.md
requirements.txt
setup.py
bin/gitver
gitver/__init__.py
gitver/_version.py
gitver/commands.py
gitver/config.py
gitver/defines.py
gitver/git.py
gitver/sanity.py
gitver/storage.py
gitver/termcolors.py
gitver/version.py
gitver.egg-info/PKG-INFO
gitver.egg-info/SOURCES.txt
gitver.egg-info/dependency_links.txt
gitver.egg-info/requires.txt
gitver.egg-info/top_level.txt