Metadata-Version: 1.1
Name: gitver
Version: 0.2.4
Summary: Simple version string management for git
Home-page: https://github.com/manuelbua/gitver
Author: Manuel Bua
Author-email: manuel.bua[at]gmail.com
License: Apache License, Version 2.0
Platform: UNKNOWN
Classifier: Development Status :: 4 - Beta
Classifier: License :: OSI Approved :: Apache Software License
Classifier: Programming Language :: Python :: 2.7
Classifier: Topic :: Software Development :: Version Control
